attrbox/__init__.py
attrbox/attrdict.py
attrbox/attrlist.py
attrbox/config.py
attrbox/env.py
attrbox/fn.py
attrbox/jsend.py
attrbox/py.typed
attrbox/_vendor/docopt/LICENSE-MIT
attrbox/_vendor/docopt/__init__.py
attrbox/_vendor/docopt/_version.py
attrbox/_vendor/docopt/py.typed
attrbox-0.1.6.dist-info/licenses/LICENSE.md
attrbox-0.1.6.dist-info/licenses/src/attrbox/_vendor/docopt/LICENSE-MIT
attrbox-0.1.6.dist-info/METADATA
attrbox-0.1.6.dist-info/WHEEL
attrbox-0.1.6.dist-info/top_level.txt
attrbox-0.1.6.dist-info/RECORD
