Metadata-Version: 2.4
Name: attrbox
Version: 0.1.6
Summary: Attribute-based data structures.
Author-email: Metaist LLC <metaist@metaist.com>
License-Expression: MIT
Project-URL: Homepage, https://github.com/metaist/attrbox
Project-URL: Documentation, https://metaist.github.io/attrbox/
Project-URL: Repository, https://github.com/metaist/attrbox.git
Project-URL: Changelog, https://github.com/metaist/attrbox/blob/main/CHANGELOG.md
Keywords: attr,attributes,dict,list
Classifier: Development Status :: 4 - Beta
Classifier: Intended Audience :: Developers
Classifier: Natural Language :: English
Classifier: Operating System :: OS Independent
Classifier: Programming Language :: Python
Classifier: Programming Language :: Python :: 3
Classifier: Programming Language :: Python :: 3 :: Only
Classifier: Programming Language :: Python :: 3.9
Classifier: Programming Language :: Python :: 3.10
Classifier: Programming Language :: Python :: 3.11
Classifier: Programming Language :: Python :: 3.12
Classifier: Programming Language :: Python :: 3.13
Classifier: Topic :: Software Development :: Libraries
Classifier: Typing :: Typed
Requires-Python: >=3.9
License-File: LICENSE.md
License-File: src/attrbox/_vendor/docopt/LICENSE-MIT
Requires-Dist: tomli==2.0.1; python_version < "3.11"
Provides-Extra: dev
Requires-Dist: coverage; extra == "dev"
Requires-Dist: ds-run; extra == "dev"
Requires-Dist: mypy; extra == "dev"
Requires-Dist: pdoc3; extra == "dev"
Requires-Dist: pyright; extra == "dev"
Requires-Dist: pytest-cov; extra == "dev"
Requires-Dist: pytest; extra == "dev"
Requires-Dist: ruff; extra == "dev"
Requires-Dist: cogapp; extra == "dev"
Dynamic: license-file
